getbook/__init__.py
getbook/cli.py
getbook/gen.py
getbook/parser.py
getbook/core/__init__.py
getbook/core/config.py
getbook/core/core_parser.py
getbook/core/fallback_parser.py
getbook/core/models.py
getbook/core/parse_content.py
getbook/core/parse_lang.py
getbook/core/parse_og.py
getbook/core/parse_schema.py
getbook/core/parse_title.py
getbook/core/post_clean.py
getbook/core/pre_clean.py
getbook/core/utils.py
getbook/ebook/__init__.py
getbook/ebook/_jinja.py
getbook/ebook/builder.py
getbook/ebook/cover.py
getbook/ebook/images.py
getbook/ebook/processor.py
getbook/ebook/static/container.xml
getbook/ebook/static/epub.css
getbook/ebook/static/highlight.css
getbook/ebook/static/layout.css
getbook/ebook/static/mobi.css
getbook/ebook/static/reset.css
getbook/ebook/templates/book.opf.xml
getbook/ebook/templates/book.preface.en.html
getbook/ebook/templates/book.preface.zh.html
getbook/ebook/templates/chapter.html
getbook/ebook/templates/cover.html
getbook/ebook/templates/section.html
getbook/ebook/templates/toc.html
getbook/sites/__init__.py
getbook/sites/feed.py
getbook/sites/github.py
getbook-0.3.dist-info/LICENSE
getbook-0.3.dist-info/METADATA
getbook-0.3.dist-info/WHEEL
getbook-0.3.dist-info/entry_points.txt
getbook-0.3.dist-info/top_level.txt
getbook-0.3.dist-info/RECORD
