Metadata-Version: 2.1
Name: getbook
Version: 0.3
Summary: Generate e-books in EPUB or MOBI from websites
Home-page: https://github.com/lepture/getbook
Author: Hsiaoming Yang
Author-email: me@lepture.com
License: GNU AGPLv3+
Platform: any
Classifier: Development Status :: 4 - Beta
Classifier: Environment :: Console
Classifier: Intended Audience :: Developers
Classifier: Operating System :: OS Independent
Classifier: Programming Language :: Python
Classifier: Programming Language :: Python :: 3
Classifier: Programming Language :: Python :: 3.5
Classifier: Programming Language :: Python :: 3.6
Classifier: Programming Language :: Python :: 3.7
Classifier: Topic :: Software Development :: Libraries :: Python Modules
Requires-Dist: beautifulsoup4
Requires-Dist: Jinja2
Requires-Dist: lxml
Requires-Dist: Pillow
Requires-Dist: python-dateutil
Requires-Dist: requests
Requires-Dist: html5lib
